emberc.cpython-312-x86_64-linux-musl.so
turbigen/__init__.py
turbigen/__main__.py
turbigen/abstract.py
turbigen/annulus.py
turbigen/average.py
turbigen/base.py
turbigen/blade.py
turbigen/camber.py
turbigen/compflow_native.py
turbigen/config2.py
turbigen/dspace.py
turbigen/exceptions.py
turbigen/flowfield.py
turbigen/fluid.py
turbigen/geometry.py
turbigen/grid.py
turbigen/hmesh.py
turbigen/inlet.py
turbigen/iterators.py
turbigen/job.py
turbigen/job_server.py
turbigen/main.py
turbigen/marching_cubes.py
turbigen/meanline_data.py
turbigen/meanline_design.py
turbigen/mesh.py
turbigen/nblade.py
turbigen/ohmesh.py
turbigen/op_point.py
turbigen/perturb.py
turbigen/polynomial.py
turbigen/post.py
turbigen/ssh.py
turbigen/state.py
turbigen/tables.py
turbigen/thickness.py
turbigen/util.py
turbigen/util_post.py
turbigen/yaml.py
turbigen/autogrid/__init__.py
turbigen/autogrid/ag_server.sh
turbigen/autogrid/autogrid.py
turbigen/autogrid/reader.py
turbigen/autogrid/script_ag.py2
turbigen/autogrid/script_igg.py2
turbigen/autogrid/script_sh
turbigen/autogrid/server.py
turbigen/clusterfunc/__init__.py
turbigen/clusterfunc/check.py
turbigen/clusterfunc/double.py
turbigen/clusterfunc/exceptions.py
turbigen/clusterfunc/plot.py
turbigen/clusterfunc/single.py
turbigen/clusterfunc/symmetric.py
turbigen/clusterfunc/util.py
turbigen/post/calc_surf_dissipation.py
turbigen/post/check_phase.py
turbigen/post/find_extrema.py
turbigen/post/plot_blade.py
turbigen/post/plot_camber.py
turbigen/post/plot_incidence.py
turbigen/post/plot_nose.py
turbigen/post/plot_section.py
turbigen/post/plot_thickness.py
turbigen/post/spanwise.py
turbigen/post/write_cuts.py
turbigen/post/write_ibl.py
turbigen/post/write_stl.py
turbigen/solvers/base.py
turbigen/solvers/convert_ts3_to_ts4_native.py
turbigen/solvers/ember.py
turbigen/solvers/external.py
turbigen/solvers/plot3d.py
turbigen/solvers/ts3.py
turbigen/solvers/ts4.py
turbigen-2.7.0.dist-info/METADATA
turbigen-2.7.0.dist-info/WHEEL
turbigen-2.7.0.dist-info/entry_points.txt
turbigen-2.7.0.dist-info/RECORD
