Metadata-Version: 2.1
Name: turbigen
Version: 2.7.0
Summary: Framework for turbomachinery design and computational fluid dynamics simulation
Keywords: turbomachinery,computational fluid dynamics,compressor,turbine
Author-Email: James Brind <jb753@cam.ac.uk>
License: GPL-3.0-or-later
Classifier: Programming Language :: Python :: 3
Classifier: License :: OSI Approved :: GNU General Public License v3 or later (GPLv3+)
Classifier: Operating System :: POSIX :: Linux
Project-URL: Homepage, https://turbigen.org
Project-URL: Repository, https://gitlab.developers.cam.ac.uk/jb753/turbigen
Requires-Python: >=3.11
Requires-Dist: CoolProp~=6.7.0
Requires-Dist: matplotlib~=3.10.0
Requires-Dist: numpy~=2.2.4
Requires-Dist: PyYAML~=6.0.0
Requires-Dist: scipy~=1.15.0
Requires-Dist: h5py~=3.13.0
Requires-Dist: numpy-stl~=3.2.0
Requires-Dist: metis~=0.2a5
Provides-Extra: parallel
Requires-Dist: mpi4py~=3.1.6; extra == "parallel"
